{
  "540171432462647307": {
    "1440694879125504292": [
      {
        "moderatorId": "AUTOMOD",
        "moderatorTag": "AutoMod",
        "reason": "AutoMod: message spam",
        "timestamp": 1763576279648
      },
      {
        "moderatorId": "AUTOMOD",
        "moderatorTag": "AutoMod",
        "reason": "AutoMod: message spam",
        "timestamp": 1763576280982
      },
      {
        "moderatorId": "AUTOMOD",
        "moderatorTag": "AutoMod",
        "reason": "AutoMod: message spam",
        "timestamp": 1763576281380
      }
    ],
    "298295566658437131": [
      {
        "moderatorId": "525890709841117187",
        "moderatorTag": "man9ixe",
        "reason": "Rule 12 - No drama /arguing.",
        "timestamp": 1765091539821
      }
    ]
  }
}